{
  "70814": {
    "modules": {
      "1016505": {
        "name": "Virtual Class",
        "rooms": {}
      },
      "1092949": {
        "name": "Week 1",
        "rooms": {
          "Video Test": {
            "RoomID": "Te6CJyK",
            "Objects": [
              {
                "name": "Sample-MP4-Video-File-for-Testing.mp4",
                "url": "https://rmit.instructure.com/files/33847982/download?download_frd=1&verifier=TQzBs7YVX8gNaGuCYS4ra3JMBgiOuNmsSB4LYtsP",
                "position": "0 2 0"
              }
            ]
          }
        }
      },
      "1099829": {
        "name": "Week 2: Mozilla Hubs",
        "rooms": {}
      }
    },
    "Quizzes": [],
    "CurrentLecture": "",
    "CurrentTutorial": "",
    "CurrentLab": "",
    "courseID": "70814"
  }
}